dash_dashboards/__init__.py
dash_dashboards/__main__.py
dash_dashboards/app/__init__.py
dash_dashboards/app/app.py
dash_dashboards/app/base_layout.py
dash_dashboards/assets/style.css
dash_dashboards/assets/img/wrong-way.svg
dash_dashboards/commands/__init__.py
dash_dashboards/commands/assets.py
dash_dashboards/commands/config.py
dash_dashboards/commands/run_server.py
dash_dashboards/commands/start_dash.py
dash_dashboards/commands/start_project.py
dash_dashboards/commands/utils.py
dash_dashboards/components/__init__.py
dash_dashboards/components/base_component.py
dash_dashboards/components/custom_dropdown.py
dash_dashboards/components/kpi.py
dash_dashboards/components/not_found.py
dash_dashboards-0.2.3.dist-info/LICENSE
dash_dashboards-0.2.3.dist-info/METADATA
dash_dashboards-0.2.3.dist-info/WHEEL
dash_dashboards-0.2.3.dist-info/entry_points.txt
dash_dashboards-0.2.3.dist-info/top_level.txt
dash_dashboards-0.2.3.dist-info/RECORD
