Metadata-Version: 2.1
Name: dash-dashboards
Version: 0.2.3
Summary: Packakge to build Dash applications
Home-page: UNKNOWN
Author: Filip Beć
License: UNKNOWN
Platform: UNKNOWN
Classifier: Programming Language :: Python :: 3
Classifier: Operating System :: OS Independent
License-File: LICENSE
Requires-Dist: click
Requires-Dist: dash-bootstrap-components
Provides-Extra: tests
Requires-Dist: isort[colors] ; extra == 'tests'
Requires-Dist: pytest ; extra == 'tests'
Requires-Dist: pytest-cov ; extra == 'tests'
Requires-Dist: pytest-env ; extra == 'tests'
Requires-Dist: flake8 ; extra == 'tests'
Requires-Dist: black ; extra == 'tests'
Requires-Dist: tox ; extra == 'tests'
